wnutils/__about__.py
wnutils/__init__.py
wnutils/base.py
wnutils/h5.py
wnutils/multi_h5.py
wnutils/multi_xml.py
wnutils/xml.py
wnutils/xsd_pub/catalog
wnutils/xsd_pub/input_nuclide_z_a.xsd
wnutils/xsd_pub/libnucnet.xsd
wnutils/xsd_pub/libnucnet__net.xsd
wnutils/xsd_pub/libnucnet__nuc.xsd
wnutils/xsd_pub/libnucnet__nuc__types.xsd
wnutils/xsd_pub/libnucnet__reac.xsd
wnutils/xsd_pub/libnucnet__reac__types.xsd
wnutils/xsd_pub/xml.xsd
wnutils/xsd_pub/zone_data.xsd
wnutils/xsd_pub/zone_data_types.xsd
wnutils-3.1.3.dist-info/licenses/LICENSE.txt
wnutils-3.1.3.dist-info/METADATA
wnutils-3.1.3.dist-info/WHEEL
wnutils-3.1.3.dist-info/top_level.txt
wnutils-3.1.3.dist-info/RECORD
