Metadata-Version: 2.4
Name: wnutils
Version: 3.1.3
Summary: Package for handling webnucleo reaction networks
Author-email: "Bradley S. Meyer" <mbradle@g.clemson.edu>
Maintainer-email: "Bradley S. Meyer" <mbradle@g.clemson.edu>
License-Expression: GPL-3.0-or-later
Project-URL: Documentation, https://wnnet.readthedocs.org
Project-URL: Repository, https://github.com/mbradle/wnnet.git
Project-URL: Bug Tracker, https://github.com/mbradle/wnnet/issues
Keywords: astronomy, nuclear astrophysics
Classifier: Development Status :: 5 - Production/Stable
Classifier: Intended Audience :: Science/Research
Classifier: Topic :: Scientific/Engineering :: Astronomy
Classifier: Programming Language :: Python :: 3
Requires-Python: >=3.0
License-File: LICENSE.txt
Requires-Dist: lxml
Requires-Dist: matplotlib
Requires-Dist: numpy
Requires-Dist: h5py
Requires-Dist: scipy
Dynamic: license-file
